hetman_kit_env/__init__.py
hetman_kit_env/core.py
hetman_kit_env/exceptions.py
hetman_kit_env-0.2.1.dist-info/licenses/LICENSE
hetman_kit_env-0.2.1.dist-info/METADATA
hetman_kit_env-0.2.1.dist-info/WHEEL
hetman_kit_env-0.2.1.dist-info/top_level.txt
hetman_kit_env-0.2.1.dist-info/RECORD
