Metadata-Version: 2.4
Name: hetman-kit-env
Version: 0.2.1
Summary: Hetman Kit Environment is a developer-centric environment variable manager. It leverages the Hetman Pipeline engine to treat environment variables not just as strings, but as strictly validated and transformed data structures.
Author-email: Hetman <degadupeko@my-relay.app>
Project-URL: Homepage, https://github.com/hetman-app/hetman-kit-env
Project-URL: Documentation, https://github.com/hetman-app/hetman-kit-env
Project-URL: Repository, https://github.com/hetman-app/hetman-kit-env
Project-URL: Issues, https://github.com/hetman-app/hetman-kit-env/issues
Classifier: Programming Language :: Python :: 3.12
Classifier: Programming Language :: Python :: 3.13
Classifier: Programming Language :: Python :: 3.14
Requires-Python: >=3.12
License-File: LICENSE
Requires-Dist: hetman-pipeline
Requires-Dist: python-dotenv
Dynamic: license-file
